Workbook

Sheet Investment Dashboard
A1: MICROSOFT | THE AI REINVESTMENT TEST
A2: Key Valuation Output | B2: Formula-Linked Result
A3: Base Implied Price | B3: ='Base DCF'!B24
A4: Reference Share Price | B4: ='Market and WACC'!B2
A5: Base Upside / Downside | B5: ='Base DCF'!B25
A6: Calculated WACC | B6: ='Market and WACC'!B16
A7: Terminal Growth | B7: ='Market and WACC'!B17
A8: Terminal Value Weight | B8: ='Base DCF'!B26
A9: D&A Accounting Status | B9: Depreciation-only input; total D&A not reconciled
A10: Research Question | B10: Can AI infrastructure investment generate sufficient returns?
A11: Annual Report | B11: https://www.sec.gov/Archives/edgar/data/789019/000119312526323660/msft-20260630.htm

Sheet Historical Financials
A1: Metric ($M) | B1: 2022 | C1: 2023 | D1: 2024 | E1: 2025 | F1: 2026
A2: Revenue | B2: 198270 | C2: 211915 | D2: 245122 | E2: 281724 | F2: 331839
A3: Operating Income | B3: 83383 | C3: 88523 | D3: 109433 | E3: 128528 | F3: 155237
A4: Net Income | B4: 72738 | C4: 72361 | D4: 88136 | E4: 101832 | F4: 133749
A5: Operating Cash Flow | B5: 89035 | C5: 87582 | D5: 118548 | E5: 136162 | F5: 182935
A6: Cash CapEx | B6: 23886 | C6: 28107 | D6: 44477 | E6: 64551 | F6: 115948
A7: Free Cash Flow | B7: 65149 | C7: 59475 | D7: 74071 | E7: 71611 | F7: 66987
A8: D&A model input (FY2026 only) | F8: 34300

Sheet Scenario Valuations
A1: Scenario | B1: Implied Price | C1: Reference Price | D1: Upside / Downside | E1: Enterprise Value ($M) | F1: Equity Value ($M) | G1: PV Terminal Weight
A2: Bear | B2: ='Bear DCF'!B24 | C2: ='Market and WACC'!B2 | D2: ='Bear DCF'!B25 | E2: ='Bear DCF'!B22 | F2: ='Bear DCF'!B23 | G2: ='Bear DCF'!B26
A3: Base | B3: ='Base DCF'!B24 | C3: ='Market and WACC'!B2 | D3: ='Base DCF'!B25 | E3: ='Base DCF'!B22 | F3: ='Base DCF'!B23 | G3: ='Base DCF'!B26
A4: Bull | B4: ='Bull DCF'!B24 | C4: ='Market and WACC'!B2 | D4: ='Bull DCF'!B25 | E4: ='Bull DCF'!B22 | F4: ='Bull DCF'!B23 | G4: ='Bull DCF'!B26

Sheet Forecast Inputs
A1: Forecast Driver | B1: 2027 | C1: 2028 | D1: 2029 | E1: 2030 | F1: 2031
A2: Revenue Growth | B2: 0.16543479 | C2: 0.15120384 | D2: 0.13697289 | E2: 0.12274194 | F2: 0.10851099
A3: EBIT Margin | B3: 0.45780818 | C3: 0.45580818 | D3: 0.45580818 | E3: 0.45780818 | F3: 0.45980818
A4: CapEx / Revenue | B4: 0.37037503 | C4: 0.34941041 | D4: 0.31796347 | E4: 0.28302243 | F4: 0.25157549
A5: D&A / Revenue | B5: 0.11369972 | C5: 0.12196879 | D5: 0.12713695 | E5: 0.12713695 | F5: 0.12403605
A6: Tax Rate | B6: 0.21 | C6: 0.21 | D6: 0.21 | E6: 0.21 | F6: 0.21
A7: Incremental NWC Ratio | B7: 0.02 | C7: 0.02 | D7: 0.02 | E7: 0.02 | F7: 0.02

Sheet Scenario Inputs
A1: Scenario | B1: Revenue Growth Adjustment | C1: EBIT Margin Adjustment | D1: CapEx / Revenue Adjustment
A2: Bear | B2: -0.035 | C2: -0.025 | D2: 0.025
A3: Base | B3: 0 | C3: 0 | D3: 0
A4: Bull | B4: 0.025 | C4: 0.02 | D4: -0.025

Sheet Market and WACC
A1: Capital Structure / Cost of Capital | B1: Value | C1: Source / Methodology
A2: Reference Price ($/share) | B2: 522.61 | C2: Yahoo Finance market snapshot
A3: Shares Outstanding (millions) | B3: 7425.5455 | C3: Yahoo Finance market snapshot
A4: Cash ($M) | B4: 20935 | C4: SEC FY2026 Form 10-K
A5: Short-Term Investments ($M) | B5: 55908 | C5: SEC FY2026 Form 10-K
A6: Current Financial Debt ($M) | B6: 9227 | C6: SEC FY2026 Form 10-K
A7: Long-Term Financial Debt ($M) | B7: 31067 | C7: SEC FY2026 Form 10-K
A8: Total Financial Debt ($M) | B8: =B6+B7 | C8: Current plus long-term financial debt
A9: Market Equity Capitalization ($M) | B9: =B2*B3 | C9: Price multiplied by shares
A10: Risk-Free Rate | B10: 0.041 | C10: Illustrative analyst assumption
A11: Equity Risk Premium | B11: 0.05 | C11: Illustrative analyst assumption
A12: Levered Equity Beta | B12: 0.95 | C12: Illustrative analyst assumption
A13: Pre-Tax Cost of Debt | B13: 0.048 | C13: Illustrative analyst assumption
A14: Marginal Tax Rate | B14: 0.21 | C14: Illustrative tax assumption
A15: Cost of Equity | B15: =B10+B11*B12 | C15: CAPM
A16: WACC | B16: =B9/(B9+B8)*B15+B8/(B9+B8)*B13*(1-B14) | C16: Market-value weighted cost of capital
A17: Terminal Growth | B17: 0.025 | C17: Long-term nominal growth assumption
A18: Valuation Timestamp UTC | B18: 2026-10-09T03:33:36+00:00 | C18: Snapshot timestamp
A19: Finance Lease Liabilities ($M) | B19: 66594 | C19: FY2026 10-K lease disclosure
A20: Operating Lease Liabilities ($M) | B20: 21925 | C20: FY2026 10-K lease disclosure
A21: New Finance Lease ROU Assets ($M) | B21: 24608 | C21: Noncash lease additions

Sheet Bear DCF
A1: Metric ($M unless stated) | B1: 2027 | C1: 2028 | D1: 2029 | E1: 2030 | F1: 2031
A2: Revenue | B2: ='Historical Financials'!F2*(1+B3) | C2: =B2*(1+C3) | D2: =C2*(1+D3) | E2: =D2*(1+E3) | F2: =E2*(1+F3)
A3: Revenue Growth | B3: ='Forecast Inputs'!B2+'Scenario Inputs'!$B$2 | C3: ='Forecast Inputs'!C2+'Scenario Inputs'!$B$2 | D3: ='Forecast Inputs'!D2+'Scenario Inputs'!$B$2 | E3: ='Forecast Inputs'!E2+'Scenario Inputs'!$B$2 | F3: ='Forecast Inputs'!F2+'Scenario Inputs'!$B$2
A4: EBIT Margin | B4: ='Forecast Inputs'!B3+'Scenario Inputs'!$C$2 | C4: ='Forecast Inputs'!C3+'Scenario Inputs'!$C$2 | D4: ='Forecast Inputs'!D3+'Scenario Inputs'!$C$2 | E4: ='Forecast Inputs'!E3+'Scenario Inputs'!$C$2 | F4: ='Forecast Inputs'!F3+'Scenario Inputs'!$C$2
A5: EBIT | B5: =B2*B4 | C5: =C2*C4 | D5: =D2*D4 | E5: =E2*E4 | F5: =F2*F4
A6: Tax Rate | B6: ='Forecast Inputs'!B6 | C6: ='Forecast Inputs'!C6 | D6: ='Forecast Inputs'!D6 | E6: ='Forecast Inputs'!E6 | F6: ='Forecast Inputs'!F6
A7: NOPAT | B7: =B5*(1-B6) | C7: =C5*(1-C6) | D7: =D5*(1-D6) | E7: =E5*(1-E6) | F7: =F5*(1-F6)
A8: D&A / Revenue | B8: ='Forecast Inputs'!B5 | C8: ='Forecast Inputs'!C5 | D8: ='Forecast Inputs'!D5 | E8: ='Forecast Inputs'!E5 | F8: ='Forecast Inputs'!F5
A9: D&A | B9: =B2*B8 | C9: =C2*C8 | D9: =D2*D8 | E9: =E2*E8 | F9: =F2*F8
A10: CapEx / Revenue | B10: ='Forecast Inputs'!B4+'Scenario Inputs'!$D$2 | C10: ='Forecast Inputs'!C4+'Scenario Inputs'!$D$2 | D10: ='Forecast Inputs'!D4+'Scenario Inputs'!$D$2 | E10: ='Forecast Inputs'!E4+'Scenario Inputs'!$D$2 | F10: ='Forecast Inputs'!F4+'Scenario Inputs'!$D$2
A11: Cash CapEx | B11: =B2*B10 | C11: =C2*C10 | D11: =D2*D10 | E11: =E2*E10 | F11: =F2*F10
A12: Incremental NWC Ratio | B12: ='Forecast Inputs'!B7 | C12: ='Forecast Inputs'!C7 | D12: ='Forecast Inputs'!D7 | E12: ='Forecast Inputs'!E7 | F12: ='Forecast Inputs'!F7
A13: Change NWC | B13: =(B2-'Historical Financials'!F2)*B12 | C13: =(C2-B2)*C12 | D13: =(D2-C2)*D12 | E13: =(E2-D2)*E12 | F13: =(F2-E2)*F12
A14: FCFF | B14: =B7+B9-B11-B13 | C14: =C7+C9-C11-C13 | D14: =D7+D9-D11-D13 | E14: =E7+E9-E11-E13 | F14: =F7+F9-F11-F13
A15: Discount Factor | B15: =1/(1+'Market and WACC'!$B$16)^1 | C15: =1/(1+'Market and WACC'!$B$16)^2 | D15: =1/(1+'Market and WACC'!$B$16)^3 | E15: =1/(1+'Market and WACC'!$B$16)^4 | F15: =1/(1+'Market and WACC'!$B$16)^5
A16: PV FCFF | B16: =B14*B15 | C16: =C14*C15 | D16: =D14*D15 | E16: =E14*E15 | F16: =F14*F15
A18: PV Forecast FCFF | B18: =SUM(B16:F16)
A19: Terminal FCFF | B19: =F14*(1+'Market and WACC'!$B$17)
A20: Terminal Value | B20: =IF('Market and WACC'!$B$16<='Market and WACC'!$B$17,NA(),B19/('Market and WACC'!$B$16-'Market and WACC'!$B$17))
A21: PV Terminal Value | B21: =B20*F15
A22: Enterprise Value | B22: =B18+B21
A23: Equity Value | B23: =B22+'Market and WACC'!B4+'Market and WACC'!B5-'Market and WACC'!B8
A24: Implied Price ($/share) | B24: =B23/'Market and WACC'!B3
A25: Upside / Downside | B25: =B24/'Market and WACC'!B2-1
A26: PV Terminal / EV | B26: =IFERROR(B21/B22,NA())

Sheet Base DCF
A1: Metric ($M unless stated) | B1: 2027 | C1: 2028 | D1: 2029 | E1: 2030 | F1: 2031
A2: Revenue | B2: ='Historical Financials'!F2*(1+B3) | C2: =B2*(1+C3) | D2: =C2*(1+D3) | E2: =D2*(1+E3) | F2: =E2*(1+F3)
A3: Revenue Growth | B3: ='Forecast Inputs'!B2+'Scenario Inputs'!$B$3 | C3: ='Forecast Inputs'!C2+'Scenario Inputs'!$B$3 | D3: ='Forecast Inputs'!D2+'Scenario Inputs'!$B$3 | E3: ='Forecast Inputs'!E2+'Scenario Inputs'!$B$3 | F3: ='Forecast Inputs'!F2+'Scenario Inputs'!$B$3
A4: EBIT Margin | B4: ='Forecast Inputs'!B3+'Scenario Inputs'!$C$3 | C4: ='Forecast Inputs'!C3+'Scenario Inputs'!$C$3 | D4: ='Forecast Inputs'!D3+'Scenario Inputs'!$C$3 | E4: ='Forecast Inputs'!E3+'Scenario Inputs'!$C$3 | F4: ='Forecast Inputs'!F3+'Scenario Inputs'!$C$3
A5: EBIT | B5: =B2*B4 | C5: =C2*C4 | D5: =D2*D4 | E5: =E2*E4 | F5: =F2*F4
A6: Tax Rate | B6: ='Forecast Inputs'!B6 | C6: ='Forecast Inputs'!C6 | D6: ='Forecast Inputs'!D6 | E6: ='Forecast Inputs'!E6 | F6: ='Forecast Inputs'!F6
A7: NOPAT | B7: =B5*(1-B6) | C7: =C5*(1-C6) | D7: =D5*(1-D6) | E7: =E5*(1-E6) | F7: =F5*(1-F6)
A8: D&A / Revenue | B8: ='Forecast Inputs'!B5 | C8: ='Forecast Inputs'!C5 | D8: ='Forecast Inputs'!D5 | E8: ='Forecast Inputs'!E5 | F8: ='Forecast Inputs'!F5
A9: D&A | B9: =B2*B8 | C9: =C2*C8 | D9: =D2*D8 | E9: =E2*E8 | F9: =F2*F8
A10: CapEx / Revenue | B10: ='Forecast Inputs'!B4+'Scenario Inputs'!$D$3 | C10: ='Forecast Inputs'!C4+'Scenario Inputs'!$D$3 | D10: ='Forecast Inputs'!D4+'Scenario Inputs'!$D$3 | E10: ='Forecast Inputs'!E4+'Scenario Inputs'!$D$3 | F10: ='Forecast Inputs'!F4+'Scenario Inputs'!$D$3
A11: Cash CapEx | B11: =B2*B10 | C11: =C2*C10 | D11: =D2*D10 | E11: =E2*E10 | F11: =F2*F10
A12: Incremental NWC Ratio | B12: ='Forecast Inputs'!B7 | C12: ='Forecast Inputs'!C7 | D12: ='Forecast Inputs'!D7 | E12: ='Forecast Inputs'!E7 | F12: ='Forecast Inputs'!F7
A13: Change NWC | B13: =(B2-'Historical Financials'!F2)*B12 | C13: =(C2-B2)*C12 | D13: =(D2-C2)*D12 | E13: =(E2-D2)*E12 | F13: =(F2-E2)*F12
A14: FCFF | B14: =B7+B9-B11-B13 | C14: =C7+C9-C11-C13 | D14: =D7+D9-D11-D13 | E14: =E7+E9-E11-E13 | F14: =F7+F9-F11-F13
A15: Discount Factor | B15: =1/(1+'Market and WACC'!$B$16)^1 | C15: =1/(1+'Market and WACC'!$B$16)^2 | D15: =1/(1+'Market and WACC'!$B$16)^3 | E15: =1/(1+'Market and WACC'!$B$16)^4 | F15: =1/(1+'Market and WACC'!$B$16)^5
A16: PV FCFF | B16: =B14*B15 | C16: =C14*C15 | D16: =D14*D15 | E16: =E14*E15 | F16: =F14*F15
A18: PV Forecast FCFF | B18: =SUM(B16:F16)
A19: Terminal FCFF | B19: =F14*(1+'Market and WACC'!$B$17)
A20: Terminal Value | B20: =IF('Market and WACC'!$B$16<='Market and WACC'!$B$17,NA(),B19/('Market and WACC'!$B$16-'Market and WACC'!$B$17))
A21: PV Terminal Value | B21: =B20*F15
A22: Enterprise Value | B22: =B18+B21
A23: Equity Value | B23: =B22+'Market and WACC'!B4+'Market and WACC'!B5-'Market and WACC'!B8
A24: Implied Price ($/share) | B24: =B23/'Market and WACC'!B3
A25: Upside / Downside | B25: =B24/'Market and WACC'!B2-1
A26: PV Terminal / EV | B26: =IFERROR(B21/B22,NA())

Sheet Bull DCF
A1: Metric ($M unless stated) | B1: 2027 | C1: 2028 | D1: 2029 | E1: 2030 | F1: 2031
A2: Revenue | B2: ='Historical Financials'!F2*(1+B3) | C2: =B2*(1+C3) | D2: =C2*(1+D3) | E2: =D2*(1+E3) | F2: =E2*(1+F3)
A3: Revenue Growth | B3: ='Forecast Inputs'!B2+'Scenario Inputs'!$B$4 | C3: ='Forecast Inputs'!C2+'Scenario Inputs'!$B$4 | D3: ='Forecast Inputs'!D2+'Scenario Inputs'!$B$4 | E3: ='Forecast Inputs'!E2+'Scenario Inputs'!$B$4 | F3: ='Forecast Inputs'!F2+'Scenario Inputs'!$B$4
A4: EBIT Margin | B4: ='Forecast Inputs'!B3+'Scenario Inputs'!$C$4 | C4: ='Forecast Inputs'!C3+'Scenario Inputs'!$C$4 | D4: ='Forecast Inputs'!D3+'Scenario Inputs'!$C$4 | E4: ='Forecast Inputs'!E3+'Scenario Inputs'!$C$4 | F4: ='Forecast Inputs'!F3+'Scenario Inputs'!$C$4
A5: EBIT | B5: =B2*B4 | C5: =C2*C4 | D5: =D2*D4 | E5: =E2*E4 | F5: =F2*F4
A6: Tax Rate | B6: ='Forecast Inputs'!B6 | C6: ='Forecast Inputs'!C6 | D6: ='Forecast Inputs'!D6 | E6: ='Forecast Inputs'!E6 | F6: ='Forecast Inputs'!F6
A7: NOPAT | B7: =B5*(1-B6) | C7: =C5*(1-C6) | D7: =D5*(1-D6) | E7: =E5*(1-E6) | F7: =F5*(1-F6)
A8: D&A / Revenue | B8: ='Forecast Inputs'!B5 | C8: ='Forecast Inputs'!C5 | D8: ='Forecast Inputs'!D5 | E8: ='Forecast Inputs'!E5 | F8: ='Forecast Inputs'!F5
A9: D&A | B9: =B2*B8 | C9: =C2*C8 | D9: =D2*D8 | E9: =E2*E8 | F9: =F2*F8
A10: CapEx / Revenue | B10: ='Forecast Inputs'!B4+'Scenario Inputs'!$D$4 | C10: ='Forecast Inputs'!C4+'Scenario Inputs'!$D$4 | D10: ='Forecast Inputs'!D4+'Scenario Inputs'!$D$4 | E10: ='Forecast Inputs'!E4+'Scenario Inputs'!$D$4 | F10: ='Forecast Inputs'!F4+'Scenario Inputs'!$D$4
A11: Cash CapEx | B11: =B2*B10 | C11: =C2*C10 | D11: =D2*D10 | E11: =E2*E10 | F11: =F2*F10
A12: Incremental NWC Ratio | B12: ='Forecast Inputs'!B7 | C12: ='Forecast Inputs'!C7 | D12: ='Forecast Inputs'!D7 | E12: ='Forecast Inputs'!E7 | F12: ='Forecast Inputs'!F7
A13: Change NWC | B13: =(B2-'Historical Financials'!F2)*B12 | C13: =(C2-B2)*C12 | D13: =(D2-C2)*D12 | E13: =(E2-D2)*E12 | F13: =(F2-E2)*F12
A14: FCFF | B14: =B7+B9-B11-B13 | C14: =C7+C9-C11-C13 | D14: =D7+D9-D11-D13 | E14: =E7+E9-E11-E13 | F14: =F7+F9-F11-F13
A15: Discount Factor | B15: =1/(1+'Market and WACC'!$B$16)^1 | C15: =1/(1+'Market and WACC'!$B$16)^2 | D15: =1/(1+'Market and WACC'!$B$16)^3 | E15: =1/(1+'Market and WACC'!$B$16)^4 | F15: =1/(1+'Market and WACC'!$B$16)^5
A16: PV FCFF | B16: =B14*B15 | C16: =C14*C15 | D16: =D14*D15 | E16: =E14*E15 | F16: =F14*F15
A18: PV Forecast FCFF | B18: =SUM(B16:F16)
A19: Terminal FCFF | B19: =F14*(1+'Market and WACC'!$B$17)
A20: Terminal Value | B20: =IF('Market and WACC'!$B$16<='Market and WACC'!$B$17,NA(),B19/('Market and WACC'!$B$16-'Market and WACC'!$B$17))
A21: PV Terminal Value | B21: =B20*F15
A22: Enterprise Value | B22: =B18+B21
A23: Equity Value | B23: =B22+'Market and WACC'!B4+'Market and WACC'!B5-'Market and WACC'!B8
A24: Implied Price ($/share) | B24: =B23/'Market and WACC'!B3
A25: Upside / Downside | B25: =B24/'Market and WACC'!B2-1
A26: PV Terminal / EV | B26: =IFERROR(B21/B22,NA())

Sheet Sensitivity
A1: WACC / Terminal Growth | B1: ='Market and WACC'!$B$17-0.010 | C1: ='Market and WACC'!$B$17-0.005 | D1: ='Market and WACC'!$B$17+0.000 | E1: ='Market and WACC'!$B$17+0.005 | F1: ='Market and WACC'!$B$17+0.010
A2: ='Market and WACC'!$B$16-0.020 | B2: =IF($A2<=B$1,NA(),(('Base DCF'!B14/(1+$A2)^1+'Base DCF'!C14/(1+$A2)^2+'Base DCF'!D14/(1+$A2)^3+'Base DCF'!E14/(1+$A2)^4+'Base DCF'!F14/(1+$A2)^5)+('Base DCF'!F14*(1+B$1)/($A2-B$1))/(1+$A2)^5+'Market and WACC'!$B$4+'Market and WACC'!$B$5-'Market and WACC'!$B$8)/'Market and WACC'!$B$3) | C2: =IF($A2<=C$1,NA(),(('Base DCF'!B14/(1+$A2)^1+'Base DCF'!C14/(1+$A2)^2+'Base DCF'!D14/(1+$A2)^3+'Base DCF'!E14/(1+$A2)^4+'Base DCF'!F14/(1+$A2)^5)+('Base DCF'!F14*(1+C$1)/($A2-C$1))/(1+$A2)^5+'Market and WACC'!$B$4+'Market and WACC'!$B$5-'Market and WACC'!$B$8)/'Market and WACC'!$B$3) | D2: =IF($A2<=D$1,NA(),(('Base DCF'!B14/(1+$A2)^1+'Base DCF'!C14/(1+$A2)^2+'Base DCF'!D14/(1+$A2)^3+'Base DCF'!E14/(1+$A2)^4+'Base DCF'!F14/(1+$A2)^5)+('Base DCF'!F14*(1+D$1)/($A2-D$1))/(1+$A2)^5+'Market and WACC'!$B$4+'Market and WACC'!$B$5-'Market and WACC'!$B$8)/'Market and WACC'!$B$3) | E2: =IF($A2<=E$1,NA(),(('Base DCF'!B14/(1+$A2)^1+'Base DCF'!C14/(1+$A2)^2+'Base DCF'!D14/(1+$A2)^3+'Base DCF'!E14/(1+$A2)^4+'Base DCF'!F14/(1+$A2)^5)+('Base DCF'!F14*(1+E$1)/($A2-E$1))/(1+$A2)^5+'Market and WACC'!$B$4+'Market and WACC'!$B$5-'Market and WACC'!$B$8)/'Market and WACC'!$B$3) | F2: =IF($A2<=F$1,NA(),(('Base DCF'!B14/(1+$A2)^1+'Base DCF'!C14/(1+$A2)^2+'Base DCF'!D14/(1+$A2)^3+'Base DCF'!E14/(1+$A2)^4+'Base DCF'!F14/(1+$A2)^5)+('Base DCF'!F14*(1+F$1)/($A2-F$1))/(1+$A2)^5+'Market and WACC'!$B$4+'Market and WACC'!$B$5-'Market and WACC'!$B$8)/'Market and WACC'!$B$3)
A3: ='Market and WACC'!$B$16-0.010 | B3: =IF($A3<=B$1,NA(),(('Base DCF'!B14/(1+$A3)^1+'Base DCF'!C14/(1+$A3)^2+'Base DCF'!D14/(1+$A3)^3+'Base DCF'!E14/(1+$A3)^4+'Base DCF'!F14/(1+$A3)^5)+('Base DCF'!F14*(1+B$1)/($A3-B$1))/(1+$A3)^5+'Market and WACC'!$B$4+'Market and WACC'!$B$5-'Market and WACC'!$B$8)/'Market and WACC'!$B$3) | C3: =IF($A3<=C$1,NA(),(('Base DCF'!B14/(1+$A3)^1+'Base DCF'!C14/(1+$A3)^2+'Base DCF'!D14/(1+$A3)^3+'Base DCF'!E14/(1+$A3)^4+'Base DCF'!F14/(1+$A3)^5)+('Base DCF'!F14*(1+C$1)/($A3-C$1))/(1+$A3)^5+'Market and WACC'!$B$4+'Market and WACC'!$B$5-'Market and WACC'!$B$8)/'Market and WACC'!$B$3) | D3: =IF($A3<=D$1,NA(),(('Base DCF'!B14/(1+$A3)^1+'Base DCF'!C14/(1+$A3)^2+'Base DCF'!D14/(1+$A3)^3+'Base DCF'!E14/(1+$A3)^4+'Base DCF'!F14/(1+$A3)^5)+('Base DCF'!F14*(1+D$1)/($A3-D$1))/(1+$A3)^5+'Market and WACC'!$B$4+'Market and WACC'!$B$5-'Market and WACC'!$B$8)/'Market and WACC'!$B$3) | E3: =IF($A3<=E$1,NA(),(('Base DCF'!B14/(1+$A3)^1+'Base DCF'!C14/(1+$A3)^2+'Base DCF'!D14/(1+$A3)^3+'Base DCF'!E14/(1+$A3)^4+'Base DCF'!F14/(1+$A3)^5)+('Base DCF'!F14*(1+E$1)/($A3-E$1))/(1+$A3)^5+'Market and WACC'!$B$4+'Market and WACC'!$B$5-'Market and WACC'!$B$8)/'Market and WACC'!$B$3) | F3: =IF($A3<=F$1,NA(),(('Base DCF'!B14/(1+$A3)^1+'Base DCF'!C14/(1+$A3)^2+'Base DCF'!D14/(1+$A3)^3+'Base DCF'!E14/(1+$A3)^4+'Base DCF'!F14/(1+$A3)^5)+('Base DCF'!F14*(1+F$1)/($A3-F$1))/(1+$A3)^5+'Market and WACC'!$B$4+'Market and WACC'!$B$5-'Market and WACC'!$B$8)/'Market and WACC'!$B$3)
A4: ='Market and WACC'!$B$16+0.000 | B4: =IF($A4<=B$1,NA(),(('Base DCF'!B14/(1+$A4)^1+'Base DCF'!C14/(1+$A4)^2+'Base DCF'!D14/(1+$A4)^3+'Base DCF'!E14/(1+$A4)^4+'Base DCF'!F14/(1+$A4)^5)+('Base DCF'!F14*(1+B$1)/($A4-B$1))/(1+$A4)^5+'Market and WACC'!$B$4+'Market and WACC'!$B$5-'Market and WACC'!$B$8)/'Market and WACC'!$B$3) | C4: =IF($A4<=C$1,NA(),(('Base DCF'!B14/(1+$A4)^1+'Base DCF'!C14/(1+$A4)^2+'Base DCF'!D14/(1+$A4)^3+'Base DCF'!E14/(1+$A4)^4+'Base DCF'!F14/(1+$A4)^5)+('Base DCF'!F14*(1+C$1)/($A4-C$1))/(1+$A4)^5+'Market and WACC'!$B$4+'Market and WACC'!$B$5-'Market and WACC'!$B$8)/'Market and WACC'!$B$3) | D4: =IF($A4<=D$1,NA(),(('Base DCF'!B14/(1+$A4)^1+'Base DCF'!C14/(1+$A4)^2+'Base DCF'!D14/(1+$A4)^3+'Base DCF'!E14/(1+$A4)^4+'Base DCF'!F14/(1+$A4)^5)+('Base DCF'!F14*(1+D$1)/($A4-D$1))/(1+$A4)^5+'Market and WACC'!$B$4+'Market and WACC'!$B$5-'Market and WACC'!$B$8)/'Market and WACC'!$B$3) | E4: =IF($A4<=E$1,NA(),(('Base DCF'!B14/(1+$A4)^1+'Base DCF'!C14/(1+$A4)^2+'Base DCF'!D14/(1+$A4)^3+'Base DCF'!E14/(1+$A4)^4+'Base DCF'!F14/(1+$A4)^5)+('Base DCF'!F14*(1+E$1)/($A4-E$1))/(1+$A4)^5+'Market and WACC'!$B$4+'Market and WACC'!$B$5-'Market and WACC'!$B$8)/'Market and WACC'!$B$3) | F4: =IF($A4<=F$1,NA(),(('Base DCF'!B14/(1+$A4)^1+'Base DCF'!C14/(1+$A4)^2+'Base DCF'!D14/(1+$A4)^3+'Base DCF'!E14/(1+$A4)^4+'Base DCF'!F14/(1+$A4)^5)+('Base DCF'!F14*(1+F$1)/($A4-F$1))/(1+$A4)^5+'Market and WACC'!$B$4+'Market and WACC'!$B$5-'Market and WACC'!$B$8)/'Market and WACC'!$B$3)
A5: ='Market and WACC'!$B$16+0.010 | B5: =IF($A5<=B$1,NA(),(('Base DCF'!B14/(1+$A5)^1+'Base DCF'!C14/(1+$A5)^2+'Base DCF'!D14/(1+$A5)^3+'Base DCF'!E14/(1+$A5)^4+'Base DCF'!F14/(1+$A5)^5)+('Base DCF'!F14*(1+B$1)/($A5-B$1))/(1+$A5)^5+'Market and WACC'!$B$4+'Market and WACC'!$B$5-'Market and WACC'!$B$8)/'Market and WACC'!$B$3) | C5: =IF($A5<=C$1,NA(),(('Base DCF'!B14/(1+$A5)^1+'Base DCF'!C14/(1+$A5)^2+'Base DCF'!D14/(1+$A5)^3+'Base DCF'!E14/(1+$A5)^4+'Base DCF'!F14/(1+$A5)^5)+('Base DCF'!F14*(1+C$1)/($A5-C$1))/(1+$A5)^5+'Market and WACC'!$B$4+'Market and WACC'!$B$5-'Market and WACC'!$B$8)/'Market and WACC'!$B$3) | D5: =IF($A5<=D$1,NA(),(('Base DCF'!B14/(1+$A5)^1+'Base DCF'!C14/(1+$A5)^2+'Base DCF'!D14/(1+$A5)^3+'Base DCF'!E14/(1+$A5)^4+'Base DCF'!F14/(1+$A5)^5)+('Base DCF'!F14*(1+D$1)/($A5-D$1))/(1+$A5)^5+'Market and WACC'!$B$4+'Market and WACC'!$B$5-'Market and WACC'!$B$8)/'Market and WACC'!$B$3) | E5: =IF($A5<=E$1,NA(),(('Base DCF'!B14/(1+$A5)^1+'Base DCF'!C14/(1+$A5)^2+'Base DCF'!D14/(1+$A5)^3+'Base DCF'!E14/(1+$A5)^4+'Base DCF'!F14/(1+$A5)^5)+('Base DCF'!F14*(1+E$1)/($A5-E$1))/(1+$A5)^5+'Market and WACC'!$B$4+'Market and WACC'!$B$5-'Market and WACC'!$B$8)/'Market and WACC'!$B$3) | F5: =IF($A5<=F$1,NA(),(('Base DCF'!B14/(1+$A5)^1+'Base DCF'!C14/(1+$A5)^2+'Base DCF'!D14/(1+$A5)^3+'Base DCF'!E14/(1+$A5)^4+'Base DCF'!F14/(1+$A5)^5)+('Base DCF'!F14*(1+F$1)/($A5-F$1))/(1+$A5)^5+'Market and WACC'!$B$4+'Market and WACC'!$B$5-'Market and WACC'!$B$8)/'Market and WACC'!$B$3)
A6: ='Market and WACC'!$B$16+0.020 | B6: =IF($A6<=B$1,NA(),(('Base DCF'!B14/(1+$A6)^1+'Base DCF'!C14/(1+$A6)^2+'Base DCF'!D14/(1+$A6)^3+'Base DCF'!E14/(1+$A6)^4+'Base DCF'!F14/(1+$A6)^5)+('Base DCF'!F14*(1+B$1)/($A6-B$1))/(1+$A6)^5+'Market and WACC'!$B$4+'Market and WACC'!$B$5-'Market and WACC'!$B$8)/'Market and WACC'!$B$3) | C6: =IF($A6<=C$1,NA(),(('Base DCF'!B14/(1+$A6)^1+'Base DCF'!C14/(1+$A6)^2+'Base DCF'!D14/(1+$A6)^3+'Base DCF'!E14/(1+$A6)^4+'Base DCF'!F14/(1+$A6)^5)+('Base DCF'!F14*(1+C$1)/($A6-C$1))/(1+$A6)^5+'Market and WACC'!$B$4+'Market and WACC'!$B$5-'Market and WACC'!$B$8)/'Market and WACC'!$B$3) | D6: =IF($A6<=D$1,NA(),(('Base DCF'!B14/(1+$A6)^1+'Base DCF'!C14/(1+$A6)^2+'Base DCF'!D14/(1+$A6)^3+'Base DCF'!E14/(1+$A6)^4+'Base DCF'!F14/(1+$A6)^5)+('Base DCF'!F14*(1+D$1)/($A6-D$1))/(1+$A6)^5+'Market and WACC'!$B$4+'Market and WACC'!$B$5-'Market and WACC'!$B$8)/'Market and WACC'!$B$3) | E6: =IF($A6<=E$1,NA(),(('Base DCF'!B14/(1+$A6)^1+'Base DCF'!C14/(1+$A6)^2+'Base DCF'!D14/(1+$A6)^3+'Base DCF'!E14/(1+$A6)^4+'Base DCF'!F14/(1+$A6)^5)+('Base DCF'!F14*(1+E$1)/($A6-E$1))/(1+$A6)^5+'Market and WACC'!$B$4+'Market and WACC'!$B$5-'Market and WACC'!$B$8)/'Market and WACC'!$B$3) | F6: =IF($A6<=F$1,NA(),(('Base DCF'!B14/(1+$A6)^1+'Base DCF'!C14/(1+$A6)^2+'Base DCF'!D14/(1+$A6)^3+'Base DCF'!E14/(1+$A6)^4+'Base DCF'!F14/(1+$A6)^5)+('Base DCF'!F14*(1+F$1)/($A6-F$1))/(1+$A6)^5+'Market and WACC'!$B$4+'Market and WACC'!$B$5-'Market and WACC'!$B$8)/'Market and WACC'!$B$3)

Sheet SEC Source Audit
A1: Fiscal Year | B1: Metric | C1: SEC Tag | D1: Filed | E1: Accession | F1: USD millions
A2: 2022 | B2: Revenue | C2: RevenueFromContractWithCustomerExcludingAssessedTax | D2: 2022-07-28 | E2: 0001564590-22-026876 | F2: 198270
A3: 2022 | B3: Operating Income | C3: OperatingIncomeLoss | D3: 2022-07-28 | E3: 0001564590-22-026876 | F3: 83383
A4: 2022 | B4: Net Income | C4: NetIncomeLoss | D4: 2022-07-28 | E4: 0001564590-22-026876 | F4: 72738
A5: 2022 | B5: Operating Cash Flow | C5: NetCashProvidedByUsedInOperatingActivities | D5: 2022-07-28 | E5: 0001564590-22-026876 | F5: 89035
A6: 2022 | B6: Cash CapEx | C6: PaymentsToAcquirePropertyPlantAndEquipment | D6: 2022-07-28 | E6: 0001564590-22-026876 | F6: 23886
A7: 2023 | B7: Revenue | C7: RevenueFromContractWithCustomerExcludingAssessedTax | D7: 2023-07-27 | E7: 0000950170-23-035122 | F7: 211915
A8: 2023 | B8: Operating Income | C8: OperatingIncomeLoss | D8: 2023-07-27 | E8: 0000950170-23-035122 | F8: 88523
A9: 2023 | B9: Net Income | C9: NetIncomeLoss | D9: 2023-07-27 | E9: 0000950170-23-035122 | F9: 72361
A10: 2023 | B10: Operating Cash Flow | C10: NetCashProvidedByUsedInOperatingActivities | D10: 2023-07-27 | E10: 0000950170-23-035122 | F10: 87582
A11: 2023 | B11: Cash CapEx | C11: PaymentsToAcquirePropertyPlantAndEquipment | D11: 2023-07-27 | E11: 0000950170-23-035122 | F11: 28107
A12: 2024 | B12: Revenue | C12: RevenueFromContractWithCustomerExcludingAssessedTax | D12: 2024-07-30 | E12: 0000950170-24-087843 | F12: 245122
A13: 2024 | B13: Operating Income | C13: OperatingIncomeLoss | D13: 2024-07-30 | E13: 0000950170-24-087843 | F13: 109433
... A30: 2026 | B30: Long-Term Debt | C30: LongTermDebtNoncurrent | D30: 2026-07-29 | E30: 0001193125-26-323660 | F30: 31067

Sheet Accounting Reconciliation
A1: Accounting Item | B1: USD Millions | C1: Interpretation
A2: FY2026 Cash PP&E Purchases | B2: 115948 | C2: Cash investing outflow used in FCFF
A3: FY2026 Reported Depreciation | B3: 34300 | C3: Not necessarily total D&A
A4: FY2026 D&A and Other | B4: 38534 | C4: Broader adjustment, not pure D&A
A5: FY2026 D&A Model Input | B5: 34300 | C5: Depreciation-only starting assumption
A6: New Finance Lease ROU Assets | B6: 24608 | C6: Noncash infrastructure investment
A7: Finance Lease Liabilities | B7: 66594 | C7: Separately disclosed lease obligation
A8: Operating Lease Liabilities | B8: 21925 | C8: Separately disclosed lease obligation

Sheet Methodology
A1: Model Methodology and Limitations
A2: Historical financials are sourced from SEC Company Facts.
A3: Forecasts are analyst assumptions, not Microsoft guidance.
A4: FCFF = EBIT x (1 - tax) + D&A - Cash CapEx - Change in NWC.
A5: WACC is calculated using CAPM and market-value capital structure.
A6: D&A uses a depreciation-only starting assumption.
A7: The D&A starting value is not verified total depreciation and amortization.
A8: Cash CapEx excludes noncash finance lease additions.
A9: A fully lease-adjusted model requires consistent cash flow and debt treatment.
A10: The equity bridge includes cash and short-term investments less financial debt.
A11: Missing short-term investments are provisionally treated as zero and flagged.
A12: Terminal value may represent a substantial portion of enterprise value.
... A16: Annual Filing: https://www.sec.gov/Archives/edgar/data/789019/000119312526323660/msft-20260630.htm
